[{"work":"http://www.wikidata.org/entity/Q1633586","workLabel":"Nakagin Capsule Tower","architect":"http://www.wikidata.org/entity/Q358502","architectLabel":"Kisho Kurokawa","style":"http://www.wikidata.org/entity/Q1503425","styleLabel":"Metabolism","coord":"Point(139.76345 35.66564)","image":"http://commons.wikimedia.org/wiki/Special:FilePath/Nakagin.jpg","sitelinks":"26","countryLabel":"Japan","cityLabel":"Ginza"},{"work":"http://www.wikidata.org/entity/Q4135315","workLabel":"Dalhousie Arts Centre","architect":"http://www.wikidata.org/entity/Q15502938","architectLabel":"Charles Fowler","style":"http://www.wikidata.org/entity/Q994776","styleLabel":"brutalist architecture","coord":"Point(-63.58856 44.63789)","image":"http://commons.wikimedia.org/wiki/Special:FilePath/Rebecca%20Cohn%20Auditorium.JPG","sitelinks":"3","countryLabel":"Canada","cityLabel":"Halifax"},{"work":"http://www.wikidata.org/entity/Q4135315","workLabel":"Dalhousie Arts Centre","architect":"http://www.wikidata.org/entity/Q15502938","architectLabel":"Charles Fowler","style":"http://www.wikidata.org/entity/Q1503425","styleLabel":"Metabolism","coord":"Point(-63.58856 44.63789)","image":"http://commons.wikimedia.org/wiki/Special:FilePath/Rebecca%20Cohn%20Auditorium.JPG","sitelinks":"3","countryLabel":"Canada","cityLabel":"Halifax"}]